README.md
setup.py
gitalysis/__init__.py
gitalysis.egg-info/PKG-INFO
gitalysis.egg-info/SOURCES.txt
gitalysis.egg-info/dependency_links.txt
gitalysis.egg-info/entry_points.txt
gitalysis.egg-info/requires.txt
gitalysis.egg-info/top_level.txt
gitalysis/analysis/__init__.py
gitalysis/analysis/punchcard.py
gitalysis/analysis/travel_path.py
gitalysis/cli/__init__.py
gitalysis/cli/analyse.py
gitalysis/cli/eat_all.py
gitalysis/cli/plot.py
gitalysis/helpers/__init__.py
gitalysis/helpers/db.py
gitalysis/helpers/list_manager.py
gitalysis/helpers/task.py
gitalysis/helpers/worker.py
gitalysis/plot/__init__.py
gitalysis/plot/comparison.py
gitalysis/plot/employee.py
gitalysis/plot/user.py
gitalysis/plot/plotting/__init__.py
gitalysis/plot/plotting/commit_punchcard.py
gitalysis/plot/plotting/commit_timeline.py
gitalysis/plot/plotting/contributor_similarity.py
gitalysis/plot/plotting/contributor_travel_path.py
gitalysis/plot/plotting/missing_time_comparison.py
gitalysis/plot/plotting/repository_changes.py